polyglot-15.10.03.dist-info/RECORD
polyglot-15.10.03.dist-info/entry_points.txt
polyglot-15.10.03.dist-info/metadata.json
polyglot-15.10.03.dist-info/top_level.txt
polyglot-15.10.03.dist-info/METADATA
polyglot-15.10.03.dist-info/DESCRIPTION.rst
polyglot-15.10.03.dist-info/WHEEL
polyglot/__main__.py
polyglot/mixins.py
polyglot/downloader.py
polyglot/decorators.py
polyglot/load.py
polyglot/__init__.py
polyglot/utils.py
polyglot/base.py
polyglot/text.py
polyglot/tag/__init__.py
polyglot/tag/base.py
polyglot/detect/__init__.py
polyglot/detect/langids.py
polyglot/detect/base.py
polyglot/transliteration/__init__.py
polyglot/transliteration/base.py
polyglot/tokenize/__init__.py
polyglot/tokenize/base.py
polyglot/mapping/expansion.py
polyglot/mapping/__init__.py
polyglot/mapping/base.py
polyglot/mapping/embeddings.py
